sleuth_automation/__init__.py
sleuth_automation/controlstats.py
sleuth_automation/templates/condor_submit.jinja
sleuth_automation/templates/scenario.jinja
sleuth_automation-3.0.3.data/scripts/create_sleuth_condor_batch.py
sleuth_automation-3.0.3.data/scripts/sleuth_run.py
sleuth_automation-3.0.3.dist-info/LICENSE
sleuth_automation-3.0.3.dist-info/METADATA
sleuth_automation-3.0.3.dist-info/WHEEL
sleuth_automation-3.0.3.dist-info/top_level.txt
sleuth_automation-3.0.3.dist-info/RECORD
