Metadata-Version: 2.1
Name: sleuth-automation
Version: 3.0.3
Summary: Python wrapper for SLEUTH urban growth model.
Home-page: http://github.com/sostenibilidad-unam/sleuth_automation
Author: Fidel Serrano, Rodrigo Garcia
Author-email: rgarcia@iecologia.unam.mx
License: GPLv3
Platform: UNKNOWN
Classifier: License :: OSI Approved :: GNU General Public License v3 (GPLv3)
Classifier: Programming Language :: Python :: 3.7
Classifier: Operating System :: Unix
Classifier: Topic :: Scientific/Engineering :: Information Analysis
Classifier: Topic :: Scientific/Engineering :: Atmospheric Science
Classifier: Intended Audience :: Science/Research
Classifier: Topic :: Scientific/Engineering
Requires-Python: >=3.7
Requires-Dist: pandas
Requires-Dist: jinja2
Requires-Dist: sh
